sqllineage/__init__.py
sqllineage/cli.py
sqllineage/drawing.py
sqllineage/exceptions.py
sqllineage/io.py
sqllineage/runner.py
sqllineage/build/asset-manifest.json
sqllineage/build/editor.worker.js
sqllineage/build/editor.worker.js.LICENSE.txt
sqllineage/build/editor.worker.js.map
sqllineage/build/favicon.ico
sqllineage/build/index.html
sqllineage/build/logo192.png
sqllineage/build/logo512.png
sqllineage/build/manifest.json
sqllineage/build/robots.txt
sqllineage/build/static/css/main.c1b86fee.css
sqllineage/build/static/css/main.c1b86fee.css.map
sqllineage/build/static/js/333.97bcedbd.chunk.js
sqllineage/build/static/js/333.97bcedbd.chunk.js.map
sqllineage/build/static/js/main.a8b33e0c.js
sqllineage/build/static/js/main.a8b33e0c.js.LICENSE.txt
sqllineage/build/static/js/main.a8b33e0c.js.map
sqllineage/build/static/media/codicon.4168b9c11e5075e9cfe6.ttf
sqllineage/core/__init__.py
sqllineage/core/analyzer.py
sqllineage/core/holders.py
sqllineage/core/models.py
sqllineage/core/parser/__init__.py
sqllineage/core/parser/sqlfluff/__init__.py
sqllineage/core/parser/sqlfluff/analyzer.py
sqllineage/core/parser/sqlfluff/holder_utils.py
sqllineage/core/parser/sqlfluff/models.py
sqllineage/core/parser/sqlfluff/utils.py
sqllineage/core/parser/sqlfluff/extractors/__init__.py
sqllineage/core/parser/sqlfluff/extractors/cte_extractor.py
sqllineage/core/parser/sqlfluff/extractors/ddl_alter_extractor.py
sqllineage/core/parser/sqlfluff/extractors/ddl_drop_extractor.py
sqllineage/core/parser/sqlfluff/extractors/dml_insert_extractor.py
sqllineage/core/parser/sqlfluff/extractors/dml_merge_extractor.py
sqllineage/core/parser/sqlfluff/extractors/dml_select_extractor.py
sqllineage/core/parser/sqlfluff/extractors/lineage_holder_extractor.py
sqllineage/core/parser/sqlfluff/extractors/noop_extractor.py
sqllineage/core/parser/sqlfluff/handlers/__init__.py
sqllineage/core/parser/sqlfluff/handlers/base.py
sqllineage/core/parser/sqlfluff/handlers/source.py
openmetadata_sqllineage-1.1.2.0.dist-info/LICENSE
openmetadata_sqllineage-1.1.2.0.dist-info/METADATA
openmetadata_sqllineage-1.1.2.0.dist-info/WHEEL
openmetadata_sqllineage-1.1.2.0.dist-info/entry_points.txt
openmetadata_sqllineage-1.1.2.0.dist-info/top_level.txt
openmetadata_sqllineage-1.1.2.0.dist-info/RECORD
