Metadata-Version: 2.1
Name: openmetadata-sqllineage
Version: 1.1.2.0
Summary: OpenMetadata SQL Lineage for Analysis Tool powered by Python and sqlfluff based on sqllineage.
Home-page: https://github.com/open-metadata/openmetadata-sqllineage
Author: OpenMetadata Committers
Classifier: Development Status :: 5 - Production/Stable
Classifier: License :: OSI Approved :: MIT License
Classifier: Operating System :: OS Independent
Classifier: Programming Language :: Python :: 3
Classifier: Programming Language :: Python :: 3.7
Classifier: Programming Language :: Python :: 3.8
Classifier: Programming Language :: Python :: 3.9
Classifier: Programming Language :: Python :: 3.10
Classifier: Programming Language :: Python :: 3.11
Classifier: Programming Language :: Python :: Implementation :: CPython
Requires-Python: >=3.7
Provides-Extra: ci
Provides-Extra: docs
License-File: LICENSE
